[
    {
        "name": "John Doe",
        "comment": "This is a comment from John Doe."
    },
    {
        "name": "Jane Smith",
        "comment": "This is a comment from Jane Smith."
    },
    {
        "name": "Alice Johnson",
        "comment": "This is a comment from Alice Johnson."
    },
    {
        "name": "Bob Brown",
        "comment": "This is a comment from Bob Brown."
    },
 
    {
        "name": "Charlie Davis",
        "comment": "This is a comment from Charlie Davis."
    },
    {
        "name": "Diana Prince",
        "comment": "This is a comment from Diana Prince."
    },
    {
        "name": "Ethan Hunt",
        "comment": "This is a comment from Ethan Hunt."
    },
    {
        "name": "Felicity Smoak",
        "comment": "This is a comment from Felicity Smoak."
    }
]